SageMakerWrapper/__init__.py
SageMakerWrapper/data.py
SageMakerWrapper/files_generation.py
SageMakerWrapper/training.py
SageMakerWrapper-0.1.10.dist-info/LICENSE
SageMakerWrapper-0.1.10.dist-info/METADATA
SageMakerWrapper-0.1.10.dist-info/WHEEL
SageMakerWrapper-0.1.10.dist-info/top_level.txt
SageMakerWrapper-0.1.10.dist-info/RECORD
