Metadata-Version: 2.1
Name: SageMakerWrapper
Version: 0.1.10
Summary: A simple wrapper for AWS Sagemaker
Home-page: https://github.com/MattiasKockum/SageMakerWrapper
Author: Mattias Kockum
Author-email: mattias@kockum.net
License-File: LICENSE
Requires-Dist: sagemaker
Requires-Dist: boto3
Requires-Dist: python-dotenv
